box_cmd/__init__.py
box_cmd/backup.py
box_cmd/cli.py
box_cmd/cmd_handler.py
box_cmd/destination.py
box_cmd/preset.py
box_cmd/progress_info.py
box_cmd/exceptions/__init__.py
box_cmd/exceptions/exceptions.py
tests/__init__.py
tests/conftest.py
tests/test_backup.py
tests/test_cli.py
tests/test_destination.py
tests/test_preset.py
box_cmd-2.0.3.dist-info/LICENSE
box_cmd-2.0.3.dist-info/METADATA
box_cmd-2.0.3.dist-info/WHEEL
box_cmd-2.0.3.dist-info/entry_points.txt
box_cmd-2.0.3.dist-info/top_level.txt
box_cmd-2.0.3.dist-info/RECORD
