Metadata-Version: 2.1
Name: box-cmd
Version: 2.0.3
Summary: A command-line tool to easily create backups of selected folders or files.
Author-email: Riley Housden <riley.t.housden@gmail.com>
Project-URL: Homepage, https://github.com/InValidFire/box
Project-URL: Bug Tracker, https://github.com/InValidFire/box/issues
Classifier: Programming Language :: Python :: 3
Classifier: License :: OSI Approved :: MIT License
Classifier: Operating System :: OS Independent
Requires-Python: >=3.7
License-File: LICENSE
Requires-Dist: jsonschema
Requires-Dist: click
Requires-Dist: tqdm
